sqs_s3_offloader/__init__.py
sqs_s3_offloader/celery_task.py
sqs_s3_offloader/s3_utils.py
sqs_s3_offloader/settings.py
sqs_s3_offloader/sqs_producer.py
sqs_s3_offloader-1.0.2.dist-info/licenses/LICENSE
sqs_s3_offloader-1.0.2.dist-info/METADATA
sqs_s3_offloader-1.0.2.dist-info/WHEEL
sqs_s3_offloader-1.0.2.dist-info/top_level.txt
sqs_s3_offloader-1.0.2.dist-info/RECORD
