Metadata-Version: 2.4
Name: sqs-s3-offloader
Version: 1.0.2
Summary: A utility to offload large messages to S3 and use SQS seamlessly
Home-page: https://github.com/aniket-dg/sqs-s3-offloader
Author: Aniket Gavali
Author-email: Aniket Gavali <aniket.dg25@gmail.com>
License: MIT License
Requires-Python: >=3.8
License-File: LICENSE
Requires-Dist: boto3>=1.28.0
Requires-Dist: celery>=5.3.0
Provides-Extra: dev
Requires-Dist: pytest; extra == "dev"
Requires-Dist: moto; extra == "dev"
Requires-Dist: coverage; extra == "dev"
Dynamic: author
Dynamic: home-page
Dynamic: license-file
Dynamic: requires-python
